README.txt
setup.py
collective/__init__.py
collective.navrootfield.egg-info/PKG-INFO
collective.navrootfield.egg-info/SOURCES.txt
collective.navrootfield.egg-info/dependency_links.txt
collective.navrootfield.egg-info/entry_points.txt
collective.navrootfield.egg-info/namespace_packages.txt
collective.navrootfield.egg-info/not-zip-safe
collective.navrootfield.egg-info/paster_plugins.txt
collective.navrootfield.egg-info/requires.txt
collective.navrootfield.egg-info/top_level.txt
collective/navrootfield/__init__.py
collective/navrootfield/configure.zcml
collective/navrootfield/navrootfield.py
docs/HISTORY.txt
docs/INSTALL.txt
docs/LICENSE.GPL
docs/LICENSE.txt